{
	"format_version": "1.8.0",
	"animations": {
		"animation.gm1_ord.chaos_machine.loop": {
			"loop": true,
			"animation_length": 20,
			"bones": {
				"arms": {
					"rotation": {
						"0.0": [0, 0, 0],
						"20.0": [0, 720, 0]
					}
				},
				"emerald_1": {
					"rotation": {
						"0.0": [0, 0, 0],
						"20.0": [0, -1440, 0]
					}
				},
				"emerald_2": {
					"rotation": {
						"0.0": [0, 0, 0],
						"20.0": [0, -1440, 0]
					}
				},
				"emerald_3": {
					"rotation": {
						"0.0": [0, 0, 0],
						"20.0": [0, -1440, 0]
					}
				},
				"emerald_4": {
					"rotation": {
						"0.0": [0, 0, 0],
						"20.0": [0, -1440, 0]
					}
				},
				"emerald_5": {
					"rotation": {
						"0.0": [0, 0, 0],
						"20.0": [0, -1440, 0]
					}
				},
				"emerald_6": {
					"rotation": {
						"0.0": [0, 0, 0],
						"20.0": [0, -1440, 0]
					}
				},
				"emerald_7": {
					"rotation": {
						"0.0": [0, 0, 0],
						"20.0": [0, -1440, 0]
					}
				}
			}
		},
		"animation.gm1_ord.chaos_machine.activated": {
			"loop": "hold_on_last_frame",
			"animation_length": 6.5,
			"bones": {
				"pedestal": {
					"scale": {
						"0.5": [1, 1, 1],
						"0.5833": [1, 0.84, 1],
						"5.25": [1, 0.84, 1],
						"5.3333": [1, 1, 1]
					}
				},
				"arms": {
					"rotation": {
						"1.1667": [0, 0, 0],
						"1.4167": [0, 30.10111, 0],
						"1.625": [0, 56.45527, 0],
						"1.8333": [0, 84.24757, 0],
						"2.0": [0, 107.76717, 0],
						"2.125": [0, 126.3154, 0],
						"2.1667": [0, 132.699, 0],
						"2.2083": [0, 139.19353, 0],
						"2.25": [0, 145.80395, 0],
						"2.2917": [0, 152.53754, 0],
						"2.3333": [0, 159.40206, 0],
						"2.375": [0, 166.40575, 0],
						"2.4167": [0, 173.56268, 0],
						"2.4583": [0, 180.8788, 0],
						"2.5": [0, 188.36406, 0],
						"2.5417": [0, 196.02922, 0],
						"2.5833": [0, 203.89956, 0],
						"2.625": [0, 211.97539, 0],
						"2.6667": [0, 220.28627, 0],
						"2.7083": [0, 228.83957, 0],
						"2.75": [0, 237.66526, 0],
						"2.7917": [0, 246.78449, 0],
						"2.8333": [0, 256.221, 0],
						"2.875": [0, 266.00486, 0],
						"2.9167": [0, 276.16828, 0],
						"2.9583": [0, 286.74975, 0],
						"3.0": [0, 297.79505, 0],
						"3.0417": [0, 309.33982, 0],
						"3.0833": [0, 321.44626, 0],
						"3.125": [0, 334.1687, 0],
						"3.1667": [0, 347.56768, 0],
						"3.2083": [0, 361.71636, 0],
						"3.25": [0, 376.68628, 0],
						"3.2917": [0, 392.54965, 0],
						"3.3333": [0, 409.37737, 0],
						"3.375": [0, 427.23097, 0],
						"3.4167": [0, 446.14907, 0],
						"3.4583": [0, 466.15024, 0],
						"3.5": [0, 487.19357, 0],
						"3.5417": [0, 509.19346, 0],
						"3.5833": [0, 532.0079, 0],
						"3.625": [0, 555.44624, 0],
						"3.6667": [0, 579.28797, 0],
						"3.75": [0, 627.29241, 0],
						"3.7917": [0, 651.07005, 0],
						"3.8333": [0, 674.5046, 0],
						"3.875": [0, 697.50002, 0],
						"3.9167": [0, 720, 0],
						"3.9583": [0, 742.83703, 0],
						"4.0": [0, 766.90741, 0],
						"4.0417": [0, 792.28342, 0],
						"4.0833": [0, 819.01534, 0],
						"4.125": [0, 847.14043, 0],
						"4.1667": [0, 876.65939, 0],
						"4.2083": [0, 907.53374, 0],
						"4.25": [0, 939.65273, 0],
						"4.2917": [0, 972.83111, 0],
						"4.3333": [0, 1006.77996, 0],
						"4.4167": [0, 1075.35836, 0],
						"4.4583": [0, 1109.0122, 0],
						"4.5": [0, 1132.76876, 0],
						"4.5417": [0, 1155.57105, 0],
						"4.5833": [0, 1177.42006, 0],
						"4.625": [0, 1198.31569, 0],
						"4.6667": [0, 1218.2684, 0],
						"4.7083": [0, 1237.276, 0],
						"4.75": [0, 1255.35071, 0],
						"4.7917": [0, 1272.49577, 0],
						"4.8333": [0, 1288.71822, 0],
						"4.875": [0, 1304.02963, 0],
						"4.9167": [0, 1318.43713, 0],
						"4.9583": [0, 1331.94878, 0],
						"5.0": [0, 1344.57897, 0],
						"5.0417": [0, 1356.33945, 0],
						"5.0833": [0, 1367.24312, 0],
						"5.125": [0, 1377.30408, 0],
						"5.1667": [0, 1386.53764, 0],
						"5.2083": [0, 1394.96028, 0],
						"5.25": [0, 1402.58971, 0],
						"5.2917": [0, 1409.44487, 0],
						"5.3333": [0, 1415.54592, 0],
						"5.375": [0, 1420.91425, 0],
						"5.4167": [0, 1425.57246, 0],
						"5.4583": [0, 1429.54145, 0],
						"5.5": [0, 1432.84886, 0],
						"5.5417": [0, 1435.52121, 0],
						"5.5833": [0, 1437.58398, 0],
						"5.625": [0, 1439.06615, 0],
						"5.6667": [0, 1440, 0]
					},
					"position": {
						"2.8333": [0, 0, 0],
						"3.9167": [0, 1.2, 0],
						"5.6667": [0, 0, 0]
					},
					"scale": {
						"2.8333": [1, 1, 1],
						"3.9167": [1.11, 0.87, 1.09],
						"5.6667": [1, 1, 1]
					}
				},
				"emerald_1": {
					"rotation": {
						"0.4583": [0, 0, 0],
						"0.5": [0, 12.82951, 0],
						"0.5417": [0, 32.0691, 0],
						"0.5833": [0, 53.05472, 0],
						"0.625": [0, 74.871, 0],
						"0.6667": [0, 97.14271, 0],
						"0.7083": [0, 119.66857, 0],
						"0.875": [0, 210.38478, 0],
						"0.9167": [0, 232.94354, 0],
						"0.9583": [0, 255.38067, 0],
						"1.0": [0, 277.67166, 0],
						"1.0417": [0, 299.7922, 0],
						"1.0833": [0, 321.71967, 0],
						"1.125": [0, 343.43253, 0],
						"1.1667": [0, 364.90988, 0],
						"1.2083": [0, 386.13103, 0],
						"1.25": [0, 407.07514, 0],
						"1.2917": [0, 427.72084, 0],
						"1.3333": [0, 448.0459, 0],
						"1.375": [0, 468.02685, 0],
						"1.4167": [0, 487.63864, 0],
						"1.4583": [0, 506.85188, 0],
						"1.5": [0, 525.63583, 0],
						"1.5417": [0, 543.96098, 0],
						"1.5833": [0, 561.7915, 0],
						"1.625": [0, 579.08736, 0],
						"1.6667": [0, 595.80353, 0],
						"1.7083": [0, 611.88899, 0],
						"1.75": [0, 627.28556, 0],
						"1.7917": [0, 641.92644, 0],
						"1.8333": [0, 655.7344, 0],
						"1.875": [0, 668.61959, 0],
						"1.9167": [0, 680.47664, 0],
						"1.9583": [0, 691.18111, 0],
						"2.0": [0, 700.55735, 0],
						"2.0417": [0, 708.43275, 0],
						"2.0833": [0, 714.52623, 0],
						"2.125": [0, 718.5295, 0],
						"2.1667": [0, 720, 0],
						"2.5417": [0, 720, 0]
					},
					"position": {
						"0.9583": [0, 0, 0],
						"1.0": [0, 0.42528, 0],
						"1.0417": [0, 1.69289, 0],
						"1.125": [0, 5.40711, 0],
						"1.1667": [0, 6.67472, 0],
						"1.2083": [0, 7.1, 0],
						"1.25": [0, 6.7542, 0],
						"1.2917": [0, 5.91584, 0],
						"1.3333": [0, 4.79714, 0],
						"1.4167": [0, 2.30286, 0],
						"1.4583": [0, 1.18416, 0],
						"1.5": [0, 0.3458, 0],
						"1.5417": [0, 0, 0],
						"1.875": [0, 0, 0],
						"3.4583": [0, 32, 0],
						"4.875": [-36, 32, 0]
					},
					"scale": {
						"3.25": [1, 1, 1],
						"4.875": [0, 0, 0]
					}
				},
				"emerald_2": {
					"rotation": {
						"0.4583": [0, 0, 0],
						"0.5": [0, 12.82951, 0],
						"0.5417": [0, 32.0691, 0],
						"0.5833": [0, 53.05472, 0],
						"0.625": [0, 74.871, 0],
						"0.6667": [0, 97.14271, 0],
						"0.7083": [0, 119.66857, 0],
						"0.875": [0, 210.38478, 0],
						"0.9167": [0, 232.94354, 0],
						"0.9583": [0, 255.38067, 0],
						"1.0": [0, 277.67166, 0],
						"1.0417": [0, 299.7922, 0],
						"1.0833": [0, 321.71967, 0],
						"1.125": [0, 343.43253, 0],
						"1.1667": [0, 364.90988, 0],
						"1.2083": [0, 386.13103, 0],
						"1.25": [0, 407.07514, 0],
						"1.2917": [0, 427.72084, 0],
						"1.3333": [0, 448.0459, 0],
						"1.375": [0, 468.02685, 0],
						"1.4167": [0, 487.63864, 0],
						"1.4583": [0, 506.85188, 0],
						"1.5": [0, 525.63583, 0],
						"1.5417": [0, 543.96098, 0],
						"1.5833": [0, 561.7915, 0],
						"1.625": [0, 579.08736, 0],
						"1.6667": [0, 595.80353, 0],
						"1.7083": [0, 611.88899, 0],
						"1.75": [0, 627.28556, 0],
						"1.7917": [0, 641.92644, 0],
						"1.8333": [0, 655.7344, 0],
						"1.875": [0, 668.61959, 0],
						"1.9167": [0, 680.47664, 0],
						"1.9583": [0, 691.18111, 0],
						"2.0": [0, 700.55735, 0],
						"2.0417": [0, 708.43275, 0],
						"2.0833": [0, 714.52623, 0],
						"2.125": [0, 718.5295, 0],
						"2.1667": [0, 720, 0],
						"2.5417": [0, 720, 0]
					},
					"position": {
						"0.7083": [0, 0, 0],
						"0.75": [0, 0.42528, 0],
						"0.7917": [0, 1.69289, 0],
						"0.875": [0, 5.40711, 0],
						"0.9167": [0, 6.67472, 0],
						"0.9583": [0, 7.1, 0],
						"1.0": [0, 6.7542, 0],
						"1.0417": [0, 5.91584, 0],
						"1.0833": [0, 4.79714, 0],
						"1.1667": [0, 2.30286, 0],
						"1.2083": [0, 1.18416, 0],
						"1.25": [0, 0.3458, 0],
						"1.2917": [0, 0, 0],
						"1.625": [0, 0, 0],
						"3.4583": [0, 32, 0],
						"4.875": [-36, 32, 0]
					},
					"scale": {
						"3.25": [1, 1, 1],
						"4.875": [0, 0, 0]
					}
				},
				"emerald_3": {
					"rotation": {
						"0.4583": [0, 0, 0],
						"0.5": [0, 12.82951, 0],
						"0.5417": [0, 32.0691, 0],
						"0.5833": [0, 53.05472, 0],
						"0.625": [0, 74.871, 0],
						"0.6667": [0, 97.14271, 0],
						"0.7083": [0, 119.66857, 0],
						"0.875": [0, 210.38478, 0],
						"0.9167": [0, 232.94354, 0],
						"0.9583": [0, 255.38067, 0],
						"1.0": [0, 277.67166, 0],
						"1.0417": [0, 299.7922, 0],
						"1.0833": [0, 321.71967, 0],
						"1.125": [0, 343.43253, 0],
						"1.1667": [0, 364.90988, 0],
						"1.2083": [0, 386.13103, 0],
						"1.25": [0, 407.07514, 0],
						"1.2917": [0, 427.72084, 0],
						"1.3333": [0, 448.0459, 0],
						"1.375": [0, 468.02685, 0],
						"1.4167": [0, 487.63864, 0],
						"1.4583": [0, 506.85188, 0],
						"1.5": [0, 525.63583, 0],
						"1.5417": [0, 543.96098, 0],
						"1.5833": [0, 561.7915, 0],
						"1.625": [0, 579.08736, 0],
						"1.6667": [0, 595.80353, 0],
						"1.7083": [0, 611.88899, 0],
						"1.75": [0, 627.28556, 0],
						"1.7917": [0, 641.92644, 0],
						"1.8333": [0, 655.7344, 0],
						"1.875": [0, 668.61959, 0],
						"1.9167": [0, 680.47664, 0],
						"1.9583": [0, 691.18111, 0],
						"2.0": [0, 700.55735, 0],
						"2.0417": [0, 708.43275, 0],
						"2.0833": [0, 714.52623, 0],
						"2.125": [0, 718.5295, 0],
						"2.1667": [0, 720, 0],
						"2.5417": [0, 720, 0]
					},
					"position": {
						"0.4583": [0, 0, 0],
						"0.5": [0, 0.42528, 0],
						"0.5417": [0, 1.69289, 0],
						"0.625": [0, 5.40711, 0],
						"0.6667": [0, 6.67472, 0],
						"0.7083": [0, 7.1, 0],
						"0.75": [0, 6.7542, 0],
						"0.7917": [0, 5.91584, 0],
						"0.8333": [0, 4.79714, 0],
						"0.9167": [0, 2.30286, 0],
						"0.9583": [0, 1.18416, 0],
						"1.0": [0, 0.3458, 0],
						"1.0417": [0, 0, 0],
						"1.375": [0, 0, 0],
						"3.0": [0, 0, 0],
						"3.4583": [0, 32, 0],
						"4.875": [-36, 32, 0]
					},
					"scale": {
						"3.25": [1, 1, 1],
						"4.875": [0, 0, 0]
					}
				},
				"emerald_4": {
					"rotation": {
						"0.4583": [0, 0, 0],
						"0.5": [0, 12.82951, 0],
						"0.5417": [0, 32.0691, 0],
						"0.5833": [0, 53.05472, 0],
						"0.625": [0, 74.871, 0],
						"0.6667": [0, 97.14271, 0],
						"0.7083": [0, 119.66857, 0],
						"0.875": [0, 210.38478, 0],
						"0.9167": [0, 232.94354, 0],
						"0.9583": [0, 255.38067, 0],
						"1.0": [0, 277.67166, 0],
						"1.0417": [0, 299.7922, 0],
						"1.0833": [0, 321.71967, 0],
						"1.125": [0, 343.43253, 0],
						"1.1667": [0, 364.90988, 0],
						"1.2083": [0, 386.13103, 0],
						"1.25": [0, 407.07514, 0],
						"1.2917": [0, 427.72084, 0],
						"1.3333": [0, 448.0459, 0],
						"1.375": [0, 468.02685, 0],
						"1.4167": [0, 487.63864, 0],
						"1.4583": [0, 506.85188, 0],
						"1.5": [0, 525.63583, 0],
						"1.5417": [0, 543.96098, 0],
						"1.5833": [0, 561.7915, 0],
						"1.625": [0, 579.08736, 0],
						"1.6667": [0, 595.80353, 0],
						"1.7083": [0, 611.88899, 0],
						"1.75": [0, 627.28556, 0],
						"1.7917": [0, 641.92644, 0],
						"1.8333": [0, 655.7344, 0],
						"1.875": [0, 668.61959, 0],
						"1.9167": [0, 680.47664, 0],
						"1.9583": [0, 691.18111, 0],
						"2.0": [0, 700.55735, 0],
						"2.0417": [0, 708.43275, 0],
						"2.0833": [0, 714.52623, 0],
						"2.125": [0, 718.5295, 0],
						"2.1667": [0, 720, 0],
						"2.5417": [0, 720, 0]
					},
					"position": {
						"2.0417": [0, 0, 0],
						"2.0833": [0, 0.42528, 0],
						"2.125": [0, 1.69289, 0],
						"2.2083": [0, 5.40711, 0],
						"2.25": [0, 6.67472, 0],
						"2.2917": [0, 7.1, 0],
						"2.3333": [0, 6.7542, 0],
						"2.375": [0, 5.91584, 0],
						"2.4167": [0, 4.79714, 0],
						"2.5": [0, 2.30286, 0],
						"2.5417": [0, 1.18416, 0],
						"2.5833": [0, 0.3458, 0],
						"2.625": [0, 0, 0],
						"2.9583": [0, 0, 0],
						"3.4583": [0, 32, 0],
						"4.875": [-36, 32, 0]
					},
					"scale": {
						"3.25": [1, 1, 1],
						"4.875": [0, 0, 0]
					}
				},
				"emerald_5": {
					"rotation": {
						"0.4583": [0, 0, 0],
						"0.5": [0, 12.82951, 0],
						"0.5417": [0, 32.0691, 0],
						"0.5833": [0, 53.05472, 0],
						"0.625": [0, 74.871, 0],
						"0.6667": [0, 97.14271, 0],
						"0.7083": [0, 119.66857, 0],
						"0.875": [0, 210.38478, 0],
						"0.9167": [0, 232.94354, 0],
						"0.9583": [0, 255.38067, 0],
						"1.0": [0, 277.67166, 0],
						"1.0417": [0, 299.7922, 0],
						"1.0833": [0, 321.71967, 0],
						"1.125": [0, 343.43253, 0],
						"1.1667": [0, 364.90988, 0],
						"1.2083": [0, 386.13103, 0],
						"1.25": [0, 407.07514, 0],
						"1.2917": [0, 427.72084, 0],
						"1.3333": [0, 448.0459, 0],
						"1.375": [0, 468.02685, 0],
						"1.4167": [0, 487.63864, 0],
						"1.4583": [0, 506.85188, 0],
						"1.5": [0, 525.63583, 0],
						"1.5417": [0, 543.96098, 0],
						"1.5833": [0, 561.7915, 0],
						"1.625": [0, 579.08736, 0],
						"1.6667": [0, 595.80353, 0],
						"1.7083": [0, 611.88899, 0],
						"1.75": [0, 627.28556, 0],
						"1.7917": [0, 641.92644, 0],
						"1.8333": [0, 655.7344, 0],
						"1.875": [0, 668.61959, 0],
						"1.9167": [0, 680.47664, 0],
						"1.9583": [0, 691.18111, 0],
						"2.0": [0, 700.55735, 0],
						"2.0417": [0, 708.43275, 0],
						"2.0833": [0, 714.52623, 0],
						"2.125": [0, 718.5295, 0],
						"2.1667": [0, 720, 0],
						"2.5417": [0, 720, 0]
					},
					"position": {
						"1.75": [0, 0, 0],
						"1.7917": [0, 0.42528, 0],
						"1.8333": [0, 1.69289, 0],
						"1.9167": [0, 5.40711, 0],
						"1.9583": [0, 6.67472, 0],
						"2.0": [0, 7.1, 0],
						"2.0417": [0, 6.7542, 0],
						"2.0833": [0, 5.91584, 0],
						"2.125": [0, 4.79714, 0],
						"2.2083": [0, 2.30286, 0],
						"2.25": [0, 1.18416, 0],
						"2.2917": [0, 0.3458, 0],
						"2.3333": [0, 0, 0],
						"2.6667": [0, 0, 0],
						"3.4583": [0, 32, 0],
						"4.875": [-36, 32, 0]
					},
					"scale": {
						"3.25": [1, 1, 1],
						"4.875": [0, 0, 0]
					}
				},
				"emerald_6": {
					"rotation": {
						"0.4583": [0, 0, 0],
						"0.5": [0, 12.82951, 0],
						"0.5417": [0, 32.0691, 0],
						"0.5833": [0, 53.05472, 0],
						"0.625": [0, 74.871, 0],
						"0.6667": [0, 97.14271, 0],
						"0.7083": [0, 119.66857, 0],
						"0.875": [0, 210.38478, 0],
						"0.9167": [0, 232.94354, 0],
						"0.9583": [0, 255.38067, 0],
						"1.0": [0, 277.67166, 0],
						"1.0417": [0, 299.7922, 0],
						"1.0833": [0, 321.71967, 0],
						"1.125": [0, 343.43253, 0],
						"1.1667": [0, 364.90988, 0],
						"1.2083": [0, 386.13103, 0],
						"1.25": [0, 407.07514, 0],
						"1.2917": [0, 427.72084, 0],
						"1.3333": [0, 448.0459, 0],
						"1.375": [0, 468.02685, 0],
						"1.4167": [0, 487.63864, 0],
						"1.4583": [0, 506.85188, 0],
						"1.5": [0, 525.63583, 0],
						"1.5417": [0, 543.96098, 0],
						"1.5833": [0, 561.7915, 0],
						"1.625": [0, 579.08736, 0],
						"1.6667": [0, 595.80353, 0],
						"1.7083": [0, 611.88899, 0],
						"1.75": [0, 627.28556, 0],
						"1.7917": [0, 641.92644, 0],
						"1.8333": [0, 655.7344, 0],
						"1.875": [0, 668.61959, 0],
						"1.9167": [0, 680.47664, 0],
						"1.9583": [0, 691.18111, 0],
						"2.0": [0, 700.55735, 0],
						"2.0417": [0, 708.43275, 0],
						"2.0833": [0, 714.52623, 0],
						"2.125": [0, 718.5295, 0],
						"2.1667": [0, 720, 0],
						"2.5417": [0, 720, 0]
					},
					"position": {
						"1.5": [0, 0, 0],
						"1.5417": [0, 0.42528, 0],
						"1.5833": [0, 1.69289, 0],
						"1.6667": [0, 5.40711, 0],
						"1.7083": [0, 6.67472, 0],
						"1.75": [0, 7.1, 0],
						"1.7917": [0, 6.7542, 0],
						"1.8333": [0, 5.91584, 0],
						"1.875": [0, 4.79714, 0],
						"1.9583": [0, 2.30286, 0],
						"2.0": [0, 1.18416, 0],
						"2.0417": [0, 0.3458, 0],
						"2.0833": [0, 0, 0],
						"2.4167": [0, 0, 0],
						"3.4583": [0, 32, 0],
						"4.875": [-36, 32, 0]
					},
					"scale": {
						"3.25": [1, 1, 1],
						"4.875": [0, 0, 0]
					}
				},
				"emerald_7": {
					"rotation": {
						"0.4583": [0, 0, 0],
						"0.5": [0, 12.82951, 0],
						"0.5417": [0, 32.0691, 0],
						"0.5833": [0, 53.05472, 0],
						"0.625": [0, 74.871, 0],
						"0.6667": [0, 97.14271, 0],
						"0.7083": [0, 119.66857, 0],
						"0.875": [0, 210.38478, 0],
						"0.9167": [0, 232.94354, 0],
						"0.9583": [0, 255.38067, 0],
						"1.0": [0, 277.67166, 0],
						"1.0417": [0, 299.7922, 0],
						"1.0833": [0, 321.71967, 0],
						"1.125": [0, 343.43253, 0],
						"1.1667": [0, 364.90988, 0],
						"1.2083": [0, 386.13103, 0],
						"1.25": [0, 407.07514, 0],
						"1.2917": [0, 427.72084, 0],
						"1.3333": [0, 448.0459, 0],
						"1.375": [0, 468.02685, 0],
						"1.4167": [0, 487.63864, 0],
						"1.4583": [0, 506.85188, 0],
						"1.5": [0, 525.63583, 0],
						"1.5417": [0, 543.96098, 0],
						"1.5833": [0, 561.7915, 0],
						"1.625": [0, 579.08736, 0],
						"1.6667": [0, 595.80353, 0],
						"1.7083": [0, 611.88899, 0],
						"1.75": [0, 627.28556, 0],
						"1.7917": [0, 641.92644, 0],
						"1.8333": [0, 655.7344, 0],
						"1.875": [0, 668.61959, 0],
						"1.9167": [0, 680.47664, 0],
						"1.9583": [0, 691.18111, 0],
						"2.0": [0, 700.55735, 0],
						"2.0417": [0, 708.43275, 0],
						"2.0833": [0, 714.52623, 0],
						"2.125": [0, 718.5295, 0],
						"2.1667": [0, 720, 0],
						"2.5417": [0, 720, 0]
					},
					"position": {
						"1.25": [0, 0, 0],
						"1.2917": [0, 0.42528, 0],
						"1.3333": [0, 1.69289, 0],
						"1.4167": [0, 5.40711, 0],
						"1.4583": [0, 6.67472, 0],
						"1.5": [0, 7.1, 0],
						"1.5417": [0, 6.7542, 0],
						"1.5833": [0, 5.91584, 0],
						"1.625": [0, 4.79714, 0],
						"1.7083": [0, 2.30286, 0],
						"1.75": [0, 1.18416, 0],
						"1.7917": [0, 0.3458, 0],
						"1.8333": [0, 0, 0],
						"2.1667": [0, 0, 0],
						"3.4583": [0, 32, 0],
						"4.875": [-36, 32, 0]
					},
					"scale": {
						"3.25": [1, 1, 1],
						"4.875": [0, 0, 0]
					}
				}
			}
		},
		"animation.gm1_ord.chaos_machine.glow": {
			"loop": true,
			"bones": {
				"glow_beam": {
					"scale": [1, "1+math.sin(query.anim_time*180)*0.5", 1]
				}
			}
		},
		"animation.gm1_ord.chaos_machine.glow_hidden": {
			"loop": true,
			"bones": {
				"glow_beam": {
					"scale": [1, 0, 1]
				}
			}
		},
		"animation.gm1_ord.chaos_machine.chaos_emerald_1": {
			"loop": "hold_on_last_frame",
			"animation_length": 2,
			"bones": {
				"emerald_1": {
					"rotation": {
						"1.0": [0, 0, 0],
						"1.25": [0, 720, 0]
					},
					"position": {
						"1.0": [0, 16, 0],
						"1.5": [0, 16, 0],
						"1.55": [0, 20, 0],
						"1.75": [0, 0, 0]
					},
					"scale": {
						"0.0": [0, 0, 0],
						"1.0": [0, 0, 0],
						"1.05": [0, 0, 0],
						"1.25": [1.25, 0.75, 1.25],
						"1.49": [1, 1, 1],
						"1.55": [1.25, 0.75, 1.25],
						"1.75": [0.75, 1.25, 0.75],
						"2.0": [1, 1, 1]
					}
				}
			}
		},
		"animation.gm1_ord.chaos_machine.chaos_emerald_1_got": {
			"loop": "hold_on_last_frame",
			"animation_length": 1,
			"bones": {
				"emerald_1": {
					"rotation": [0, 720, 0],
					"position": [0, 0, 0],
					"scale": 1
				}
			}
		},
		"animation.gm1_ord.chaos_machine.chaos_emerald_2": {
			"loop": "hold_on_last_frame",
			"animation_length": 2,
			"bones": {
				"emerald_2": {
					"rotation": {
						"1.0": [0, 0, 0],
						"1.25": [0, 720, 0]
					},
					"position": {
						"1.0": [0, 16, 0],
						"1.5": [0, 16, 0],
						"1.55": [0, 20, 0],
						"1.75": [0, 0, 0]
					},
					"scale": {
						"0.0": [0, 0, 0],
						"1.0": [0, 0, 0],
						"1.05": [0, 0, 0],
						"1.25": [1.25, 0.75, 1.25],
						"1.49": [1, 1, 1],
						"1.55": [1.25, 0.75, 1.25],
						"1.75": [0.75, 1.25, 0.75],
						"2.0": [1, 1, 1]
					}
				}
			}
		},
		"animation.gm1_ord.chaos_machine.chaos_emerald_2_got": {
			"loop": "hold_on_last_frame",
			"animation_length": 1,
			"bones": {
				"emerald_2": {
					"rotation": [0, 720, 0],
					"position": [0, 0, 0],
					"scale": 1
				}
			}
		},
		"animation.gm1_ord.chaos_machine.chaos_emerald_3": {
			"loop": "hold_on_last_frame",
			"animation_length": 2,
			"bones": {
				"emerald_3": {
					"rotation": {
						"1.0": [0, 0, 0],
						"1.25": [0, 720, 0]
					},
					"position": {
						"1.0": [0, 16, 0],
						"1.5": [0, 16, 0],
						"1.55": [0, 20, 0],
						"1.75": [0, 0, 0]
					},
					"scale": {
						"0.0": [0, 0, 0],
						"1.0": [0, 0, 0],
						"1.05": [0, 0, 0],
						"1.25": [1.25, 0.75, 1.25],
						"1.49": [1, 1, 1],
						"1.55": [1.25, 0.75, 1.25],
						"1.75": [0.75, 1.25, 0.75],
						"2.0": [1, 1, 1]
					}
				}
			}
		},
		"animation.gm1_ord.chaos_machine.chaos_emerald_3_got": {
			"loop": "hold_on_last_frame",
			"animation_length": 1,
			"bones": {
				"emerald_3": {
					"rotation": [0, 720, 0],
					"position": [0, 0, 0],
					"scale": 1
				}
			}
		},
		"animation.gm1_ord.chaos_machine.chaos_emerald_4": {
			"loop": "hold_on_last_frame",
			"animation_length": 2,
			"bones": {
				"emerald_4": {
					"rotation": {
						"1.0": [0, 0, 0],
						"1.25": [0, 720, 0]
					},
					"position": {
						"1.0": [0, 16, 0],
						"1.5": [0, 16, 0],
						"1.55": [0, 20, 0],
						"1.75": [0, 0, 0]
					},
					"scale": {
						"0.0": [0, 0, 0],
						"1.0": [0, 0, 0],
						"1.05": [0, 0, 0],
						"1.25": [1.25, 0.75, 1.25],
						"1.49": [1, 1, 1],
						"1.55": [1.25, 0.75, 1.25],
						"1.75": [0.75, 1.25, 0.75],
						"2.0": [1, 1, 1]
					}
				}
			}
		},
		"animation.gm1_ord.chaos_machine.chaos_emerald_4_got": {
			"loop": "hold_on_last_frame",
			"animation_length": 1,
			"bones": {
				"emerald_4": {
					"rotation": [0, 720, 0],
					"position": [0, 0, 0],
					"scale": 1
				}
			}
		},
		"animation.gm1_ord.chaos_machine.chaos_emerald_5": {
			"loop": "hold_on_last_frame",
			"animation_length": 2,
			"bones": {
				"emerald_5": {
					"rotation": {
						"1.0": [0, 0, 0],
						"1.25": [0, 720, 0]
					},
					"position": {
						"1.0": [0, 16, 0],
						"1.5": [0, 16, 0],
						"1.55": [0, 20, 0],
						"1.75": [0, 0, 0]
					},
					"scale": {
						"0.0": [0, 0, 0],
						"1.0": [0, 0, 0],
						"1.05": [0, 0, 0],
						"1.25": [1.25, 0.75, 1.25],
						"1.49": [1, 1, 1],
						"1.55": [1.25, 0.75, 1.25],
						"1.75": [0.75, 1.25, 0.75],
						"2.0": [1, 1, 1]
					}
				}
			}
		},
		"animation.gm1_ord.chaos_machine.chaos_emerald_5_got": {
			"loop": "hold_on_last_frame",
			"animation_length": 1,
			"bones": {
				"emerald_5": {
					"rotation": [0, 720, 0],
					"position": [0, 0, 0],
					"scale": 1
				}
			}
		},
		"animation.gm1_ord.chaos_machine.chaos_emerald_6": {
			"loop": "hold_on_last_frame",
			"animation_length": 2,
			"bones": {
				"emerald_6": {
					"rotation": {
						"1.0": [0, 0, 0],
						"1.25": [0, 720, 0]
					},
					"position": {
						"1.0": [0, 16, 0],
						"1.5": [0, 16, 0],
						"1.55": [0, 20, 0],
						"1.75": [0, 0, 0]
					},
					"scale": {
						"0.0": [0, 0, 0],
						"1.0": [0, 0, 0],
						"1.05": [0, 0, 0],
						"1.25": [1.25, 0.75, 1.25],
						"1.49": [1, 1, 1],
						"1.55": [1.25, 0.75, 1.25],
						"1.75": [0.75, 1.25, 0.75],
						"2.0": [1, 1, 1]
					}
				}
			}
		},
		"animation.gm1_ord.chaos_machine.chaos_emerald_6_got": {
			"loop": "hold_on_last_frame",
			"animation_length": 1,
			"bones": {
				"emerald_6": {
					"rotation": [0, 720, 0],
					"position": [0, 0, 0],
					"scale": 1
				}
			}
		},
		"animation.gm1_ord.chaos_machine.chaos_emerald_7": {
			"loop": "hold_on_last_frame",
			"animation_length": 2,
			"bones": {
				"emerald_7": {
					"rotation": {
						"1.0": [0, 0, 0],
						"1.25": [0, 720, 0]
					},
					"position": {
						"1.0": [0, 16, 0],
						"1.5": [0, 16, 0],
						"1.55": [0, 20, 0],
						"1.75": [0, 0, 0]
					},
					"scale": {
						"0.0": [0, 0, 0],
						"1.0": [0, 0, 0],
						"1.05": [0, 0, 0],
						"1.25": [1.25, 0.75, 1.25],
						"1.49": [1, 1, 1],
						"1.55": [1.25, 0.75, 1.25],
						"1.75": [0.75, 1.25, 0.75],
						"2.0": [1, 1, 1]
					}
				}
			}
		},
		"animation.gm1_ord.chaos_machine.chaos_emerald_7_got": {
			"loop": "hold_on_last_frame",
			"animation_length": 1,
			"bones": {
				"emerald_7": {
					"rotation": [0, 720, 0],
					"position": [0, 0, 0],
					"scale": 1
				}
			}
		},
		"animation.gm1_ord.chaos_machine.empty_1": {
			"loop": "hold_on_last_frame",
			"animation_length": 1,
			"bones": {
				"emerald_1": {
					"scale": {
						"0.0": [0, 0, 0]
					}
				}
			}
		},
		"animation.gm1_ord.chaos_machine.empty_2": {
			"loop": "hold_on_last_frame",
			"animation_length": 1,
			"bones": {
				"emerald_2": {
					"scale": {
						"0.0": [0, 0, 0]
					}
				}
			}
		},
		"animation.gm1_ord.chaos_machine.empty_3": {
			"loop": "hold_on_last_frame",
			"animation_length": 1,
			"bones": {
				"emerald_3": {
					"scale": {
						"0.0": [0, 0, 0]
					}
				}
			}
		},
		"animation.gm1_ord.chaos_machine.empty_4": {
			"loop": "hold_on_last_frame",
			"animation_length": 1,
			"bones": {
				"emerald_4": {
					"scale": {
						"0.0": [0, 0, 0]
					}
				}
			}
		},
		"animation.gm1_ord.chaos_machine.empty_5": {
			"loop": "hold_on_last_frame",
			"animation_length": 1,
			"bones": {
				"emerald_5": {
					"scale": {
						"0.0": [0, 0, 0]
					}
				}
			}
		},
		"animation.gm1_ord.chaos_machine.empty_6": {
			"loop": "hold_on_last_frame",
			"animation_length": 1,
			"bones": {
				"emerald_6": {
					"scale": {
						"0.0": [0, 0, 0]
					}
				}
			}
		},
		"animation.gm1_ord.chaos_machine.empty_7": {
			"loop": "hold_on_last_frame",
			"animation_length": 1,
			"bones": {
				"emerald_7": {
					"scale": {
						"0.0": [0, 0, 0]
					}
				}
			}
		}
	}
}